<?xml version = '1.0' encoding = 'UTF-8'?>
<TableProxySqlServerv2k5 class="oracle.dbtools.crest.model.design.storage.sqlserver.v2k5.TableProxySqlServerv2k5" name="dim_tipos_ingresos_causas" directorySegmentName="seg_0" id="4E5E63A6-D0ED-D0F8-4DFB-D4C148AD5A05">
<createdBy>omanriquez</createdBy>
<createdTime>2023-09-14 15:29:05 UTC</createdTime>
<ownerDesignName>dwh_familia</ownerDesignName>
<schemaObject>81C2A2E0-6765-0143-51F5-2E9396AC4EF9</schemaObject>
<database>DB40E2D3-1A35-AC09-0F84-1791275E2157</database>
<filegroup>1338E6E9-2176-8EF9-696E-76AC88A4CC1B</filegroup>
<schema>1</schema>
<columnProxies>
<ColumnProxy class="oracle.dbtools.crest.model.design.storage.sqlserver.v2k5.ColumnProxySqlServerv2k5" name="fecha_creacion" id="404AFD40-06E4-6C9C-BB16-A673EE2DAAEF">
<createdBy>omanriquez</createdBy>
<createdTime>2023-09-14 15:29:05 UTC</createdTime>
<ownerDesignName>dwh_familia</ownerDesignName>
</ColumnProxy>
<ColumnProxy class="oracle.dbtools.crest.model.design.storage.sqlserver.v2k5.ColumnProxySqlServerv2k5" name="fecha_modificacion" id="6617E370-75F0-266E-0C9C-98C32AE77CBF">
<createdBy>omanriquez</createdBy>
<createdTime>2023-09-14 15:29:05 UTC</createdTime>
<ownerDesignName>dwh_familia</ownerDesignName>
</ColumnProxy>
<ColumnProxy class="oracle.dbtools.crest.model.design.storage.sqlserver.v2k5.ColumnProxySqlServerv2k5" name="tipo_ingreso_causa_id" id="80E8BB30-87F1-8821-33CF-101136243CC5">
<createdBy>omanriquez</createdBy>
<createdTime>2023-09-14 15:29:05 UTC</createdTime>
<ownerDesignName>dwh_familia</ownerDesignName>
<asIdentity>true</asIdentity>
<identityForReplication>YES</identityForReplication>
</ColumnProxy>
<ColumnProxy class="oracle.dbtools.crest.model.design.storage.sqlserver.v2k5.ColumnProxySqlServerv2k5" name="tip_ing_causa" id="BD4EC36C-E465-4B3A-B335-1EEF6DC7AA21">
<createdBy>omanriquez</createdBy>
<createdTime>2023-09-14 15:29:05 UTC</createdTime>
<ownerDesignName>dwh_familia</ownerDesignName>
</ColumnProxy>
<ColumnProxy class="oracle.dbtools.crest.model.design.storage.sqlserver.v2k5.ColumnProxySqlServerv2k5" name="gls_ing_causa" id="FD710C5D-466C-3730-75E0-A96214F82BA1">
<createdBy>omanriquez</createdBy>
<createdTime>2023-09-14 15:29:05 UTC</createdTime>
<ownerDesignName>dwh_familia</ownerDesignName>
<collation>Modern_Spanish_CI_AS</collation>
</ColumnProxy>
</columnProxies>
<indexProxies>
<IndexProxy class="oracle.dbtools.crest.model.design.storage.sqlserver.v2k5.IndexProxySqlServerv2k5" name="index_1v8" id="974B3B0E-867B-551A-91B6-E430CDB65CC0">
<createdBy>omanriquez</createdBy>
<createdTime>2023-09-14 15:29:05 UTC</createdTime>
<ownerDesignName>dwh_familia</ownerDesignName>
<clustered>true</clustered>
<fileGroup>1338E6E9-2176-8EF9-696E-76AC88A4CC1B</fileGroup>
<recomputeStatistics>OFF</recomputeStatistics>
</IndexProxy>
</indexProxies>
<primaryKeys>
<PrimaryKey class="oracle.dbtools.crest.model.design.storage.sqlserver.v2k5.PKProxySqlServerv2k5" name="PK_dim_tipos_ingresos_causas" id="C47C9ED6-70D7-1B83-8639-61A48808D543">
<createdBy>omanriquez</createdBy>
<createdTime>2023-09-14 15:29:05 UTC</createdTime>
<ownerDesignName>dwh_familia</ownerDesignName>
<fileGroup>1338E6E9-2176-8EF9-696E-76AC88A4CC1B</fileGroup>
<recomputeStatistics>NO</recomputeStatistics>
</PrimaryKey>
</primaryKeys>
</TableProxySqlServerv2k5>